msgpack/__init__.py
msgpack/_cmsgpack.cpython-312.so
msgpack/exceptions.py
msgpack/ext.py
msgpack/fallback.py
msgpack_qpython-1.1.0.1.dist-info/METADATA
msgpack_qpython-1.1.0.1.dist-info/WHEEL
msgpack_qpython-1.1.0.1.dist-info/top_level.txt
msgpack_qpython-1.1.0.1.dist-info/RECORD
